Workbook

Sheet Start Here
A1: Stage-Pay Tracker
A2: Build at home from abroad. No proof, no payment.
B5: How it works
A6: 1 | C6: Fill in the Project tab: your builder's name, location and start date.
A7: 2 | C7: On the Stages tab, enter the agreed price for each stage. Rename or adjust stages to match your contract.
A8: 3 | C8: Check the Proof Checklist. Each stage has a list of photos, videos and receipts to ask for. Add or remove items to suit your build.
A9: 4 | C9: Before paying for a stage, open the WhatsApp tab. It writes the message asking for any missing proof. Copy it and send it to your builder.
A10: 5 | C10: As proof arrives, set 'Received?' to Yes on the Proof Checklist. Paste a link to where you saved the photo or video.
A11: 6 | C11: Every time you send money, add a row to the Payments tab. The Dashboard updates by itself.
B13: The rule
A14: • | C14: A stage is Verified only when money has been sent AND every proof item is received.
A15: • | C15: The next stage stays Locked until the previous one is Verified. Don't send money to a locked stage.
A16: • | C16: 'Unproven' on the Dashboard is money you've sent that isn't backed by proof yet. Aim to keep it at $0 before each new payment.
B18: Colour key
B19: Yellow cells: type here
B20: White cells: worked out for you, so don't type over them
B22: Tabs
B23: Dashboard: totals, progress and your next step
B24: Project: your project details
B25: Stages: agreed price, money sent and status for each stage
B26: Payments: every transfer you make
B27: Proof Checklist: what to ask for at each stage, and what you've received
B28: WhatsApp: ready-to-send messages for your builder and family
B29: Before You Build: checks to do first, and red flags to watch for
B31: Using Google Sheets
... B35: Stage-Pay is a record-keeping tool. It isn't legal, financial or engineering advice, and it can't guarantee how a builder behaves. For large projects, consider an independent inspector or engineer to check the work on site.

Sheet Dashboard
B1: =IF(Project!$B$4="","My build",Project!$B$4) -> My build
B2: =IF(Project!$B$5="","Fill in the Project tab to get started",Project!$B$5&" · Builder: "&Project!$B$6) -> Fill in the Project tab to get started
B4: Total budget | C4: Sent | D4: Verified built | E4: Unproven | F4: Budget left
B5: =SUM(Stages!C6:C15) -> 0 | C5: =SUM(Stages!D6:D15) -> 0 | D5: =SUMIF(Stages!I6:I15,"Verified",Stages!D6:D15) -> 0 | E5: =C5-D5 -> 0 | F5: =B5-C5 -> 0
B7: Verified | C7: =IF($B$5=0,0,$D$5/$B$5) -> 0 | D7: =REPT("█",ROUND(C7*40,0))
B8: Sent, no proof yet | C8: =IF($B$5=0,0,$E$5/$B$5) -> 0 | D8: =REPT("█",ROUND(C8*40,0))
B9: (Bars show share of total budget)
B11: Where you are now
B12: Current stage | C12: =IFERROR(INDEX(Stages!B6:B15,MATCH(1,Stages!K6:K15,0)),"All stages verified 🎉") -> Foundation & footings
B13: Status | C13: =IFERROR(INDEX(Stages!I6:I15,MATCH(1,Stages!K6:K15,0)),"Verified") -> Ready to fund
B14: Next step | C14: =IFERROR(INDEX(Stages!J6:J15,MATCH(1,Stages!K6:K15,0)),"Well done. Keep all receipts and photos safe.") -> Agree the amount and send proof list before paying.
B15: Payment warnings | C15: =IF(COUNTIF(Payments!H6:H205,"⚠*")=0,"None","⚠ "&COUNTIF(Payments!H6:H205,"⚠*")&" payment(s) sent before the previous stage was verified") -> None
B17: All stages
B18: Stage | C18: Agreed | D18: Sent | E18: Proof | F18: Status
B19: =IF(Stages!B6="","",Stages!A6&". "&Stages!B6) -> 1. Foundation & footings | C19: =IF(Stages!B6="","",Stages!C6) -> 0 | D19: =IF(Stages!B6="","",Stages!D6) -> 0 | E19: =IF(Stages!B6="","",Stages!G6&" of "&Stages!F6) -> 0 of 6 | F19: =Stages!I6 -> Ready to fund
B20: =IF(Stages!B7="","",Stages!A7&". "&Stages!B7) -> 2. Slab level (DPC & floor slab) | C20: =IF(Stages!B7="","",Stages!C7) -> 0 | D20: =IF(Stages!B7="","",Stages!D7) -> 0 | E20: =IF(Stages!B7="","",Stages!G7&" of "&Stages!F7) -> 0 of 6 | F20: =Stages!I7 -> Locked
B21: =IF(Stages!B8="","",Stages!A8&". "&Stages!B8) -> 3. Window level | C21: =IF(Stages!B8="","",Stages!C8) -> 0 | D21: =IF(Stages!B8="","",Stages!D8) -> 0 | E21: =IF(Stages!B8="","",Stages!G8&" of "&Stages!F8) -> 0 of 5 | F21: =Stages!I8 -> Locked
B22: =IF(Stages!B9="","",Stages!A9&". "&Stages!B9) -> 4. Roof level (lintels & wall plate) | C22: =IF(Stages!B9="","",Stages!C9) -> 0 | D22: =IF(Stages!B9="","",Stages!D9) -> 0 | E22: =IF(Stages!B9="","",Stages!G9&" of "&Stages!F9) -> 0 of 5 | F22: =Stages!I9 -> Locked
B23: =IF(Stages!B10="","",Stages!A10&". "&Stages!B10) -> 5. Roofing | C23: =IF(Stages!B10="","",Stages!C10) -> 0 | D23: =IF(Stages!B10="","",Stages!D10) -> 0 | E23: =IF(Stages!B10="","",Stages!G10&" of "&Stages!F10) -> 0 of 5 | F23: =Stages!I10 -> Locked
B24: =IF(Stages!B11="","",Stages!A11&". "&Stages!B11) -> 6. Plumbing & electrical (first fix) | C24: =IF(Stages!B11="","",Stages!C11) -> 0 | D24: =IF(Stages!B11="","",Stages!D11) -> 0 | E24: =IF(Stages!B11="","",Stages!G11&" of "&Stages!F11) -> 0 of 5 | F24: =Stages!I11 -> Locked
B25: =IF(Stages!B12="","",Stages!A12&". "&Stages!B12) -> 7. Plaster & ceilings | C25: =IF(Stages!B12="","",Stages!C12) -> 0 | D25: =IF(Stages!B12="","",Stages!D12) -> 0 | E25: =IF(Stages!B12="","",Stages!G12&" of "&Stages!F12) -> 0 of 4 | F25: =Stages!I12 -> Locked
B26: =IF(Stages!B13="","",Stages!A13&". "&Stages!B13) -> 8. Floors, doors & finishing | C26: =IF(Stages!B13="","",Stages!C13) -> 0 | D26: =IF(Stages!B13="","",Stages!D13) -> 0 | E26: =IF(Stages!B13="","",Stages!G13&" of "&Stages!F13) -> 0 of 6 | F26: =Stages!I13 -> Locked
B27: =IF(Stages!B14="","",Stages!A14&". "&Stages!B14) | C27: =IF(Stages!B14="","",Stages!C14) | D27: =IF(Stages!B14="","",Stages!D14) | E27: =IF(Stages!B14="","",Stages!G14&" of "&Stages!F14) | F27: =Stages!I14
B28: =IF(Stages!B15="","",Stages!A15&". "&Stages!B15) | C28: =IF(Stages!B15="","",Stages!C15) | D28: =IF(Stages!B15="","",Stages!D15) | E28: =IF(Stages!B15="","",Stages!G15&" of "&Stages!F15) | F28: =Stages!I15

Sheet Project
A1: Project details
A2: Fill in the yellow cells.
A4: Project name | C4: e.g. 4-room house
A5: Location / stand number | C5: e.g. Stand 1234, Chitungwiza
A6: Builder name | C6: Used in your WhatsApp messages
A7: Builder WhatsApp number
A8: Site contact (family or friend) | C8: Someone you trust who can visit the site
A9: Start date
A10: Currency | B10: USD | C10: All amounts in this tracker use this currency

Sheet Stages
A1: Stages
A2: Enter the agreed price for each stage (yellow). Everything else updates from the Payments and Proof Checklist tabs.
A5: # | B5: Stage | C5: Agreed price | D5: Sent | E5: Left to pay | F5: Proof items | G5: Proof received | H5: Proof % | I5: Status | J5: Next step | K5: Open?
A6: 1 | B6: Foundation & footings | D6: =SUMIF(Payments!$B$6:$B$205,A6,Payments!$D$6:$D$205) -> 0 | E6: =IF(B6="","",C6-D6) -> 0 | F6: =COUNTIFS('Proof Checklist'!$A$6:$A$155,A6,'Proof Checklist'!$C$6:$C$155,"<>") -> 6 | G6: =COUNTIFS('Proof Checklist'!$A$6:$A$155,A6,'Proof Checklist'!$D$6:$D$155,"Yes") -> 0 | H6: =IF(F6=0,0,G6/F6) -> 0 | I6: =IF(B6="","",IF(F6=0,"Add proof items",IF(AND(D6>0,G6>=F6),"Verified",IF(NOT(TRUE()),"Locked",IF(D6>0,"Hold payment","Ready to fund"))))) -> Ready to fund | J6: =IF(I6="","",IF(I6="Verified","Done. All proof received.",IF(I6="Locked","Wait. Don't send money until the previous stage is verified.",IF(I6="Hold payment","Hold. "&(F6-G6)&" proof item(s) missing. Send the WhatsApp request.",IF(I6="Ready to fund","Agree the amount and send proof list before paying.","Add proof items on the Proof Checklist tab."))))) -> Agree the amount and send proof list before paying. | K6: =IF(AND(B6<>"",I6<>"Verified"),1,0) -> 1
A7: 2 | B7: Slab level (DPC & floor slab) | D7: =SUMIF(Payments!$B$6:$B$205,A7,Payments!$D$6:$D$205) -> 0 | E7: =IF(B7="","",C7-D7) -> 0 | F7: =COUNTIFS('Proof Checklist'!$A$6:$A$155,A7,'Proof Checklist'!$C$6:$C$155,"<>") -> 6 | G7: =COUNTIFS('Proof Checklist'!$A$6:$A$155,A7,'Proof Checklist'!$D$6:$D$155,"Yes") -> 0 | H7: =IF(F7=0,0,G7/F7) -> 0 | I7: =IF(B7="","",IF(F7=0,"Add proof items",IF(AND(D7>0,G7>=F7),"Verified",IF(NOT(I6="Verified"),"Locked",IF(D7>0,"Hold payment","Ready to fund"))))) -> Locked | J7: =IF(I7="","",IF(I7="Verified","Done. All proof received.",IF(I7="Locked","Wait. Don't send money until the previous stage is verified.",IF(I7="Hold payment","Hold. "&(F7-G7)&" proof item(s) missing. Send the WhatsApp request.",IF(I7="Ready to fund","Agree the amount and send proof list before paying.","Add proof items on the Proof Checklist tab."))))) -> Wait. Don't send money until the previous stage is verified. | K7: =IF(AND(B7<>"",I7<>"Verified"),1,0) -> 1
A8: 3 | B8: Window level | D8: =SUMIF(Payments!$B$6:$B$205,A8,Payments!$D$6:$D$205) -> 0 | E8: =IF(B8="","",C8-D8) -> 0 | F8: =COUNTIFS('Proof Checklist'!$A$6:$A$155,A8,'Proof Checklist'!$C$6:$C$155,"<>") -> 5 | G8: =COUNTIFS('Proof Checklist'!$A$6:$A$155,A8,'Proof Checklist'!$D$6:$D$155,"Yes") -> 0 | H8: =IF(F8=0,0,G8/F8) -> 0 | I8: =IF(B8="","",IF(F8=0,"Add proof items",IF(AND(D8>0,G8>=F8),"Verified",IF(NOT(I7="Verified"),"Locked",IF(D8>0,"Hold payment","Ready to fund"))))) -> Locked | J8: =IF(I8="","",IF(I8="Verified","Done. All proof received.",IF(I8="Locked","Wait. Don't send money until the previous stage is verified.",IF(I8="Hold payment","Hold. "&(F8-G8)&" proof item(s) missing. Send the WhatsApp request.",IF(I8="Ready to fund","Agree the amount and send proof list before paying.","Add proof items on the Proof Checklist tab."))))) -> Wait. Don't send money until the previous stage is verified. | K8: =IF(AND(B8<>"",I8<>"Verified"),1,0) -> 1
A9: 4 | B9: Roof level (lintels & wall plate) | D9: =SUMIF(Payments!$B$6:$B$205,A9,Payments!$D$6:$D$205) -> 0 | E9: =IF(B9="","",C9-D9) -> 0 | F9: =COUNTIFS('Proof Checklist'!$A$6:$A$155,A9,'Proof Checklist'!$C$6:$C$155,"<>") -> 5 | G9: =COUNTIFS('Proof Checklist'!$A$6:$A$155,A9,'Proof Checklist'!$D$6:$D$155,"Yes") -> 0 | H9: =IF(F9=0,0,G9/F9) -> 0 | I9: =IF(B9="","",IF(F9=0,"Add proof items",IF(AND(D9>0,G9>=F9),"Verified",IF(NOT(I8="Verified"),"Locked",IF(D9>0,"Hold payment","Ready to fund"))))) -> Locked | J9: =IF(I9="","",IF(I9="Verified","Done. All proof received.",IF(I9="Locked","Wait. Don't send money until the previous stage is verified.",IF(I9="Hold payment","Hold. "&(F9-G9)&" proof item(s) missing. Send the WhatsApp request.",IF(I9="Ready to fund","Agree the amount and send proof list before paying.","Add proof items on the Proof Checklist tab."))))) -> Wait. Don't send money until the previous stage is verified. | K9: =IF(AND(B9<>"",I9<>"Verified"),1,0) -> 1
A10: 5 | B10: Roofing | D10: =SUMIF(Payments!$B$6:$B$205,A10,Payments!$D$6:$D$205) -> 0 | E10: =IF(B10="","",C10-D10) -> 0 | F10: =COUNTIFS('Proof Checklist'!$A$6:$A$155,A10,'Proof Checklist'!$C$6:$C$155,"<>") -> 5 | G10: =COUNTIFS('Proof Checklist'!$A$6:$A$155,A10,'Proof Checklist'!$D$6:$D$155,"Yes") -> 0 | H10: =IF(F10=0,0,G10/F10) -> 0 | I10: =IF(B10="","",IF(F10=0,"Add proof items",IF(AND(D10>0,G10>=F10),"Verified",IF(NOT(I9="Verified"),"Locked",IF(D10>0,"Hold payment","Ready to fund"))))) -> Locked | J10: =IF(I10="","",IF(I10="Verified","Done. All proof received.",IF(I10="Locked","Wait. Don't send money until the previous stage is verified.",IF(I10="Hold payment","Hold. "&(F10-G10)&" proof item(s) missing. Send the WhatsApp request.",IF(I10="Ready to fund","Agree the amount and send proof list before paying.","Add proof items on the Proof Checklist tab."))))) -> Wait. Don't send money until the previous stage is verified. | K10: =IF(AND(B10<>"",I10<>"Verified"),1,0) -> 1
A11: 6 | B11: Plumbing & electrical (first fix) | D11: =SUMIF(Payments!$B$6:$B$205,A11,Payments!$D$6:$D$205) -> 0 | E11: =IF(B11="","",C11-D11) -> 0 | F11: =COUNTIFS('Proof Checklist'!$A$6:$A$155,A11,'Proof Checklist'!$C$6:$C$155,"<>") -> 5 | G11: =COUNTIFS('Proof Checklist'!$A$6:$A$155,A11,'Proof Checklist'!$D$6:$D$155,"Yes") -> 0 | H11: =IF(F11=0,0,G11/F11) -> 0 | I11: =IF(B11="","",IF(F11=0,"Add proof items",IF(AND(D11>0,G11>=F11),"Verified",IF(NOT(I10="Verified"),"Locked",IF(D11>0,"Hold payment","Ready to fund"))))) -> Locked | J11: =IF(I11="","",IF(I11="Verified","Done. All proof received.",IF(I11="Locked","Wait. Don't send money until the previous stage is verified.",IF(I11="Hold payment","Hold. "&(F11-G11)&" proof item(s) missing. Send the WhatsApp request.",IF(I11="Ready to fund","Agree the amount and send proof list before paying.","Add proof items on the Proof Checklist tab."))))) -> Wait. Don't send money until the previous stage is verified. | K11: =IF(AND(B11<>"",I11<>"Verified"),1,0) -> 1
A12: 7 | B12: Plaster & ceilings | D12: =SUMIF(Payments!$B$6:$B$205,A12,Payments!$D$6:$D$205) -> 0 | E12: =IF(B12="","",C12-D12) -> 0 | F12: =COUNTIFS('Proof Checklist'!$A$6:$A$155,A12,'Proof Checklist'!$C$6:$C$155,"<>") -> 4 | G12: =COUNTIFS('Proof Checklist'!$A$6:$A$155,A12,'Proof Checklist'!$D$6:$D$155,"Yes") -> 0 | H12: =IF(F12=0,0,G12/F12) -> 0 | I12: =IF(B12="","",IF(F12=0,"Add proof items",IF(AND(D12>0,G12>=F12),"Verified",IF(NOT(I11="Verified"),"Locked",IF(D12>0,"Hold payment","Ready to fund"))))) -> Locked | J12: =IF(I12="","",IF(I12="Verified","Done. All proof received.",IF(I12="Locked","Wait. Don't send money until the previous stage is verified.",IF(I12="Hold payment","Hold. "&(F12-G12)&" proof item(s) missing. Send the WhatsApp request.",IF(I12="Ready to fund","Agree the amount and send proof list before paying.","Add proof items on the Proof Checklist tab."))))) -> Wait. Don't send money until the previous stage is verified. | K12: =IF(AND(B12<>"",I12<>"Verified"),1,0) -> 1
A13: 8 | B13: Floors, doors & finishing | D13: =SUMIF(Payments!$B$6:$B$205,A13,Payments!$D$6:$D$205) -> 0 | E13: =IF(B13="","",C13-D13) -> 0 | F13: =COUNTIFS('Proof Checklist'!$A$6:$A$155,A13,'Proof Checklist'!$C$6:$C$155,"<>") -> 6 | G13: =COUNTIFS('Proof Checklist'!$A$6:$A$155,A13,'Proof Checklist'!$D$6:$D$155,"Yes") -> 0 | H13: =IF(F13=0,0,G13/F13) -> 0 | I13: =IF(B13="","",IF(F13=0,"Add proof items",IF(AND(D13>0,G13>=F13),"Verified",IF(NOT(I12="Verified"),"Locked",IF(D13>0,"Hold payment","Ready to fund"))))) -> Locked | J13: =IF(I13="","",IF(I13="Verified","Done. All proof received.",IF(I13="Locked","Wait. Don't send money until the previous stage is verified.",IF(I13="Hold payment","Hold. "&(F13-G13)&" proof item(s) missing. Send the WhatsApp request.",IF(I13="Ready to fund","Agree the amount and send proof list before paying.","Add proof items on the Proof Checklist tab."))))) -> Wait. Don't send money until the previous stage is verified. | K13: =IF(AND(B13<>"",I13<>"Verified"),1,0) -> 1
A14: 9 | D14: =SUMIF(Payments!$B$6:$B$205,A14,Payments!$D$6:$D$205) -> 0 | E14: =IF(B14="","",C14-D14) | F14: =COUNTIFS('Proof Checklist'!$A$6:$A$155,A14,'Proof Checklist'!$C$6:$C$155,"<>") -> 0 | G14: =COUNTIFS('Proof Checklist'!$A$6:$A$155,A14,'Proof Checklist'!$D$6:$D$155,"Yes") -> 0 | H14: =IF(F14=0,0,G14/F14) -> 0 | I14: =IF(B14="","",IF(F14=0,"Add proof items",IF(AND(D14>0,G14>=F14),"Verified",IF(NOT(I13="Verified"),"Locked",IF(D14>0,"Hold payment","Ready to fund"))))) | J14: =IF(I14="","",IF(I14="Verified","Done. All proof received.",IF(I14="Locked","Wait. Don't send money until the previous stage is verified.",IF(I14="Hold payment","Hold. "&(F14-G14)&" proof item(s) missing. Send the WhatsApp request.",IF(I14="Ready to fund","Agree the amount and send proof list before paying.","Add proof items on the Proof Checklist tab."))))) | K14: =IF(AND(B14<>"",I14<>"Verified"),1,0) -> 0
A15: 10 | D15: =SUMIF(Payments!$B$6:$B$205,A15,Payments!$D$6:$D$205) -> 0 | E15: =IF(B15="","",C15-D15) | F15: =COUNTIFS('Proof Checklist'!$A$6:$A$155,A15,'Proof Checklist'!$C$6:$C$155,"<>") -> 0 | G15: =COUNTIFS('Proof Checklist'!$A$6:$A$155,A15,'Proof Checklist'!$D$6:$D$155,"Yes") -> 0 | H15: =IF(F15=0,0,G15/F15) -> 0 | I15: =IF(B15="","",IF(F15=0,"Add proof items",IF(AND(D15>0,G15>=F15),"Verified",IF(NOT(I14="Verified"),"Locked",IF(D15>0,"Hold payment","Ready to fund"))))) | J15: =IF(I15="","",IF(I15="Verified","Done. All proof received.",IF(I15="Locked","Wait. Don't send money until the previous stage is verified.",IF(I15="Hold payment","Hold. "&(F15-G15)&" proof item(s) missing. Send the WhatsApp request.",IF(I15="Ready to fund","Agree the amount and send proof list before paying.","Add proof items on the Proof Checklist tab."))))) | K15: =IF(AND(B15<>"",I15<>"Verified"),1,0) -> 0
B16: Total | C16: =SUM(C6:C15) -> 0 | D16: =SUM(D6:D15) -> 0 | E16: =SUM(E6:E15) -> 0
B18: Rows 9 and 10 are spare. Type a stage name to use them. 'Open?' is a helper column the Dashboard uses.

Sheet Payments
A1: Payments
A2: Add a row every time you send money. Pick the stage number (1–10) the money is for.
A4: Example of a filled row: 4 Mar 2026 | 1 | (stage fills in) | $3,000 | Mukuru | Tendai M. | Foundation materials
A5: Date | B5: Stage # | C5: Stage | D5: Amount | E5: Method | F5: Paid to | G5: What it was for / reference | H5: Check | J5: Total sent
C6: =IF(B6="","",IFERROR(INDEX(Stages!$B$6:$B$15,B6),"Unknown stage")) | H6: =IF(B6="","",IF(B6=1,"OK",IF(IFERROR(INDEX(Stages!$I$6:$I$15,B6-1),"")="Verified","OK","⚠ Previous stage not verified yet"))) | J6: =SUM(D6:D205) -> 0
C7: =IF(B7="","",IFERROR(INDEX(Stages!$B$6:$B$15,B7),"Unknown stage")) | H7: =IF(B7="","",IF(B7=1,"OK",IF(IFERROR(INDEX(Stages!$I$6:$I$15,B7-1),"")="Verified","OK","⚠ Previous stage not verified yet")))
C8: =IF(B8="","",IFERROR(INDEX(Stages!$B$6:$B$15,B8),"Unknown stage")) | H8: =IF(B8="","",IF(B8=1,"OK",IF(IFERROR(INDEX(Stages!$I$6:$I$15,B8-1),"")="Verified","OK","⚠ Previous stage not verified yet")))
C9: =IF(B9="","",IFERROR(INDEX(Stages!$B$6:$B$15,B9),"Unknown stage")) | H9: =IF(B9="","",IF(B9=1,"OK",IF(IFERROR(INDEX(Stages!$I$6:$I$15,B9-1),"")="Verified","OK","⚠ Previous stage not verified yet")))
C10: =IF(B10="","",IFERROR(INDEX(Stages!$B$6:$B$15,B10),"Unknown stage")) | H10: =IF(B10="","",IF(B10=1,"OK",IF(IFERROR(INDEX(Stages!$I$6:$I$15,B10-1),"")="Verified","OK","⚠ Previous stage not verified yet")))
C11: =IF(B11="","",IFERROR(INDEX(Stages!$B$6:$B$15,B11),"Unknown stage")) | H11: =IF(B11="","",IF(B11=1,"OK",IF(IFERROR(INDEX(Stages!$I$6:$I$15,B11-1),"")="Verified","OK","⚠ Previous stage not verified yet")))
C12: =IF(B12="","",IFERROR(INDEX(Stages!$B$6:$B$15,B12),"Unknown stage")) | H12: =IF(B12="","",IF(B12=1,"OK",IF(IFERROR(INDEX(Stages!$I$6:$I$15,B12-1),"")="Verified","OK","⚠ Previous stage not verified yet")))
C13: =IF(B13="","",IFERROR(INDEX(Stages!$B$6:$B$15,B13),"Unknown stage")) | H13: =IF(B13="","",IF(B13=1,"OK",IF(IFERROR(INDEX(Stages!$I$6:$I$15,B13-1),"")="Verified","OK","⚠ Previous stage not verified yet")))
C14: =IF(B14="","",IFERROR(INDEX(Stages!$B$6:$B$15,B14),"Unknown stage")) | H14: =IF(B14="","",IF(B14=1,"OK",IF(IFERROR(INDEX(Stages!$I$6:$I$15,B14-1),"")="Verified","OK","⚠ Previous stage not verified yet")))
C15: =IF(B15="","",IFERROR(INDEX(Stages!$B$6:$B$15,B15),"Unknown stage")) | H15: =IF(B15="","",IF(B15=1,"OK",IF(IFERROR(INDEX(Stages!$I$6:$I$15,B15-1),"")="Verified","OK","⚠ Previous stage not verified yet")))
C16: =IF(B16="","",IFERROR(INDEX(Stages!$B$6:$B$15,B16),"Unknown stage")) | H16: =IF(B16="","",IF(B16=1,"OK",IF(IFERROR(INDEX(Stages!$I$6:$I$15,B16-1),"")="Verified","OK","⚠ Previous stage not verified yet")))
C17: =IF(B17="","",IFERROR(INDEX(Stages!$B$6:$B$15,B17),"Unknown stage")) | H17: =IF(B17="","",IF(B17=1,"OK",IF(IFERROR(INDEX(Stages!$I$6:$I$15,B17-1),"")="Verified","OK","⚠ Previous stage not verified yet")))
C18: =IF(B18="","",IFERROR(INDEX(Stages!$B$6:$B$15,B18),"Unknown stage")) | H18: =IF(B18="","",IF(B18=1,"OK",IF(IFERROR(INDEX(Stages!$I$6:$I$15,B18-1),"")="Verified","OK","⚠ Previous stage not verified yet")))
... C205: =IF(B205="","",IFERROR(INDEX(Stages!$B$6:$B$15,B205),"Unknown stage")) | H205: =IF(B205="","",IF(B205=1,"OK",IF(IFERROR(INDEX(Stages!$I$6:$I$15,B205-1),"")="Verified","OK","⚠ Previous stage not verified yet")))

Sheet Proof Checklist
A1: Proof Checklist
A2: What to ask for before each stage is paid. Set 'Received?' to Yes when it arrives. Add your own items in the empty rows at the bottom.
A5: Stage # | B5: Stage | C5: Proof to ask for | D5: Received? | E5: Date received | F5: Where it's saved (link or note) | G5: msg
A6: 1 | B6: =IF(A6="","",IFERROR(INDEX(Stages!$B$6:$B$15,A6),"")) -> Foundation & footings | C6: Setting-out photo: pegs and strings match the approved plan | D6: No | G6: =IF(AND(A6=WhatsApp!$C$5,C6<>"",D6<>"Yes"),COUNTIFS($A$6:A6,WhatsApp!$C$5,$C$6:C6,"<>",$D$6:D6,"<>Yes"),"") -> 1
A7: 1 | B7: =IF(A7="","",IFERROR(INDEX(Stages!$B$6:$B$15,A7),"")) -> Foundation & footings | C7: Trenches with a tape measure showing depth and width | D7: No | G7: =IF(AND(A7=WhatsApp!$C$5,C7<>"",D7<>"Yes"),COUNTIFS($A$6:A7,WhatsApp!$C$5,$C$6:C7,"<>",$D$6:D7,"<>Yes"),"") -> 2
A8: 1 | B8: =IF(A8="","",IFERROR(INDEX(Stages!$B$6:$B$15,A8),"")) -> Foundation & footings | C8: Footings poured: photo of every trench | D8: No | G8: =IF(AND(A8=WhatsApp!$C$5,C8<>"",D8<>"Yes"),COUNTIFS($A$6:A8,WhatsApp!$C$5,$C$6:C8,"<>",$D$6:D8,"<>Yes"),"") -> 3
A9: 1 | B9: =IF(A9="","",IFERROR(INDEX(Stages!$B$6:$B$15,A9),"")) -> Foundation & footings | C9: Foundation brickwork up to ground level: photo of each side | D9: No | G9: =IF(AND(A9=WhatsApp!$C$5,C9<>"",D9<>"Yes"),COUNTIFS($A$6:A9,WhatsApp!$C$5,$C$6:C9,"<>",$D$6:D9,"<>Yes"),"") -> 4
A10: 1 | B10: =IF(A10="","",IFERROR(INDEX(Stages!$B$6:$B$15,A10),"")) -> Foundation & footings | C10: Video walking round the whole foundation | D10: No | G10: =IF(AND(A10=WhatsApp!$C$5,C10<>"",D10<>"Yes"),COUNTIFS($A$6:A10,WhatsApp!$C$5,$C$6:C10,"<>",$D$6:D10,"<>Yes"),"") -> 5
A11: 1 | B11: =IF(A11="","",IFERROR(INDEX(Stages!$B$6:$B$15,A11),"")) -> Foundation & footings | C11: Receipts: cement, sand, stone, bricks | D11: No | G11: =IF(AND(A11=WhatsApp!$C$5,C11<>"",D11<>"Yes"),COUNTIFS($A$6:A11,WhatsApp!$C$5,$C$6:C11,"<>",$D$6:D11,"<>Yes"),"") -> 6
A12: 2 | B12: =IF(A12="","",IFERROR(INDEX(Stages!$B$6:$B$15,A12),"")) -> Slab level (DPC & floor slab) | C12: Brickwork to slab level: photo of each side | D12: No | G12: =IF(AND(A12=WhatsApp!$C$5,C12<>"",D12<>"Yes"),COUNTIFS($A$6:A12,WhatsApp!$C$5,$C$6:C12,"<>",$D$6:D12,"<>Yes"),"")
A13: 2 | B13: =IF(A13="","",IFERROR(INDEX(Stages!$B$6:$B$15,A13),"")) -> Slab level (DPC & floor slab) | C13: Damp-proof course (DPC) visible all round | D13: No | G13: =IF(AND(A13=WhatsApp!$C$5,C13<>"",D13<>"Yes"),COUNTIFS($A$6:A13,WhatsApp!$C$5,$C$6:C13,"<>",$D$6:D13,"<>Yes"),"")
A14: 2 | B14: =IF(A14="","",IFERROR(INDEX(Stages!$B$6:$B$15,A14),"")) -> Slab level (DPC & floor slab) | C14: Hardcore filled and compacted | D14: No | G14: =IF(AND(A14=WhatsApp!$C$5,C14<>"",D14<>"Yes"),COUNTIFS($A$6:A14,WhatsApp!$C$5,$C$6:C14,"<>",$D$6:D14,"<>Yes"),"")
A15: 2 | B15: =IF(A15="","",IFERROR(INDEX(Stages!$B$6:$B$15,A15),"")) -> Slab level (DPC & floor slab) | C15: Slab poured: photo across the whole floor | D15: No | G15: =IF(AND(A15=WhatsApp!$C$5,C15<>"",D15<>"Yes"),COUNTIFS($A$6:A15,WhatsApp!$C$5,$C$6:C15,"<>",$D$6:D15,"<>Yes"),"")
A16: 2 | B16: =IF(A16="","",IFERROR(INDEX(Stages!$B$6:$B$15,A16),"")) -> Slab level (DPC & floor slab) | C16: Receipts: cement, mesh, DPC, hardcore | D16: No | G16: =IF(AND(A16=WhatsApp!$C$5,C16<>"",D16<>"Yes"),COUNTIFS($A$6:A16,WhatsApp!$C$5,$C$6:C16,"<>",$D$6:D16,"<>Yes"),"")
A17: 2 | B17: =IF(A17="","",IFERROR(INDEX(Stages!$B$6:$B$15,A17),"")) -> Slab level (DPC & floor slab) | C17: Council stage inspection signed (if your council requires it) | D17: No | G17: =IF(AND(A17=WhatsApp!$C$5,C17<>"",D17<>"Yes"),COUNTIFS($A$6:A17,WhatsApp!$C$5,$C$6:C17,"<>",$D$6:D17,"<>Yes"),"")
... A47: 8 | B47: =IF(A47="","",IFERROR(INDEX(Stages!$B$6:$B$15,A47),"")) -> Floors, doors & finishing | C47: Final receipts and handover of keys | D47: No | G47: =IF(AND(A47=WhatsApp!$C$5,C47<>"",D47<>"Yes"),COUNTIFS($A$6:A47,WhatsApp!$C$5,$C$6:C47,"<>",$D$6:D47,"<>Yes"),"")
B48: =IF(A48="","",IFERROR(INDEX(Stages!$B$6:$B$15,A48),"")) | G48: =IF(AND(A48=WhatsApp!$C$5,C48<>"",D48<>"Yes"),COUNTIFS($A$6:A48,WhatsApp!$C$5,$C$6:C48,"<>",$D$6:D48,"<>Yes"),"")
B49: =IF(A49="","",IFERROR(INDEX(Stages!$B$6:$B$15,A49),"")) | G49: =IF(AND(A49=WhatsApp!$C$5,C49<>"",D49<>"Yes"),COUNTIFS($A$6:A49,WhatsApp!$C$5,$C$6:C49,"<>",$D$6:D49,"<>Yes"),"")
B50: =IF(A50="","",IFERROR(INDEX(Stages!$B$6:$B$15,A50),"")) | G50: =IF(AND(A50=WhatsApp!$C$5,C50<>"",D50<>"Yes"),COUNTIFS($A$6:A50,WhatsApp!$C$5,$C$6:C50,"<>",$D$6:D50,"<>Yes"),"")
B51: =IF(A51="","",IFERROR(INDEX(Stages!$B$6:$B$15,A51),"")) | G51: =IF(AND(A51=WhatsApp!$C$5,C51<>"",D51<>"Yes"),COUNTIFS($A$6:A51,WhatsApp!$C$5,$C$6:C51,"<>",$D$6:D51,"<>Yes"),"")
B52: =IF(A52="","",IFERROR(INDEX(Stages!$B$6:$B$15,A52),"")) | G52: =IF(AND(A52=WhatsApp!$C$5,C52<>"",D52<>"Yes"),COUNTIFS($A$6:A52,WhatsApp!$C$5,$C$6:C52,"<>",$D$6:D52,"<>Yes"),"")
B53: =IF(A53="","",IFERROR(INDEX(Stages!$B$6:$B$15,A53),"")) | G53: =IF(AND(A53=WhatsApp!$C$5,C53<>"",D53<>"Yes"),COUNTIFS($A$6:A53,WhatsApp!$C$5,$C$6:C53,"<>",$D$6:D53,"<>Yes"),"")
B54: =IF(A54="","",IFERROR(INDEX(Stages!$B$6:$B$15,A54),"")) | G54: =IF(AND(A54=WhatsApp!$C$5,C54<>"",D54<>"Yes"),COUNTIFS($A$6:A54,WhatsApp!$C$5,$C$6:C54,"<>",$D$6:D54,"<>Yes"),"")
B55: =IF(A55="","",IFERROR(INDEX(Stages!$B$6:$B$15,A55),"")) | G55: =IF(AND(A55=WhatsApp!$C$5,C55<>"",D55<>"Yes"),COUNTIFS($A$6:A55,WhatsApp!$C$5,$C$6:C55,"<>",$D$6:D55,"<>Yes"),"")
B56: =IF(A56="","",IFERROR(INDEX(Stages!$B$6:$B$15,A56),"")) | G56: =IF(AND(A56=WhatsApp!$C$5,C56<>"",D56<>"Yes"),COUNTIFS($A$6:A56,WhatsApp!$C$5,$C$6:C56,"<>",$D$6:D56,"<>Yes"),"")
B57: =IF(A57="","",IFERROR(INDEX(Stages!$B$6:$B$15,A57),"")) | G57: =IF(AND(A57=WhatsApp!$C$5,C57<>"",D57<>"Yes"),COUNTIFS($A$6:A57,WhatsApp!$C$5,$C$6:C57,"<>",$D$6:D57,"<>Yes"),"")
B58: =IF(A58="","",IFERROR(INDEX(Stages!$B$6:$B$15,A58),"")) | G58: =IF(AND(A58=WhatsApp!$C$5,C58<>"",D58<>"Yes"),COUNTIFS($A$6:A58,WhatsApp!$C$5,$C$6:C58,"<>",$D$6:D58,"<>Yes"),"")
B59: =IF(A59="","",IFERROR(INDEX(Stages!$B$6:$B$15,A59),"")) | G59: =IF(AND(A59=WhatsApp!$C$5,C59<>"",D59<>"Yes"),COUNTIFS($A$6:A59,WhatsApp!$C$5,$C$6:C59,"<>",$D$6:D59,"<>Yes"),"")
... B155: =IF(A155="","",IFERROR(INDEX(Stages!$B$6:$B$15,A155),"")) | G155: =IF(AND(A155=WhatsApp!$C$5,C155<>"",D155<>"Yes"),COUNTIFS($A$6:A155,WhatsApp!$C$5,$C$6:C155,"<>",$D$6:D155,"<>Yes"),"")

Sheet WhatsApp
A1: WhatsApp messages
A2: Copy a message, paste it into WhatsApp and send. Your builder's name comes from the Project tab.
B5: Stage to ask about | C5: =IFERROR(MATCH(1,Stages!$K$6:$K$15,0),10) -> 1 | D5: ← Picks your current stage. Type a different number (1–10) to change it.
B6: Stage name | C6: =IFERROR(INDEX(Stages!$B$6:$B$15,C5),"") -> Foundation & footings
B8: Missing proof
B9: 1 | C9: =IFERROR(INDEX('Proof Checklist'!$C$6:$C$155,MATCH(1,'Proof Checklist'!$G$6:$G$155,0)),"") -> Setting-out photo: pegs and strings match the approved plan
B10: 2 | C10: =IFERROR(INDEX('Proof Checklist'!$C$6:$C$155,MATCH(2,'Proof Checklist'!$G$6:$G$155,0)),"") -> Trenches with a tape measure showing depth and width
B11: 3 | C11: =IFERROR(INDEX('Proof Checklist'!$C$6:$C$155,MATCH(3,'Proof Checklist'!$G$6:$G$155,0)),"") -> Footings poured: photo of every trench
B12: 4 | C12: =IFERROR(INDEX('Proof Checklist'!$C$6:$C$155,MATCH(4,'Proof Checklist'!$G$6:$G$155,0)),"") -> Foundation brickwork up to ground level: photo of each side
B13: 5 | C13: =IFERROR(INDEX('Proof Checklist'!$C$6:$C$155,MATCH(5,'Proof Checklist'!$G$6:$G$155,0)),"") -> Video walking round the whole foundation
B14: 6 | C14: =IFERROR(INDEX('Proof Checklist'!$C$6:$C$155,MATCH(6,'Proof Checklist'!$G$6:$G$155,0)),"") -> Receipts: cement, sand, stone, bricks
B15: 7 | C15: =IFERROR(INDEX('Proof Checklist'!$C$6:$C$155,MATCH(7,'Proof Checklist'!$G$6:$G$155,0)),"")
B16: 8 | C16: =IFERROR(INDEX('Proof Checklist'!$C$6:$C$155,MATCH(8,'Proof Checklist'!$G$6:$G$155,0)),"")
B17: 9 | C17: =IFERROR(INDEX('Proof Checklist'!$C$6:$C$155,MATCH(9,'Proof Checklist'!$G$6:$G$155,0)),"")
B18: 10 | C18: =IFERROR(INDEX('Proof Checklist'!$C$6:$C$155,MATCH(10,'Proof Checklist'!$G$6:$G$155,0)),"")
B20: Message: ask for missing proof
B21: Copy the cell on the right → | C21: =IF(C9="","Hi "&IF(Project!$B$6="","there",Project!$B$6)&", thank you. All the proof for "&LOWER(C6)&" is in. I'll send the payment today.","Hi "&IF(Project!$B$6="","there",Project!$B$6)&", hope you and the team are well. Before I send the next payment for "&LOWER(C6)&", please send:"&IF(C9="","",CHAR(10)&"1. "&C9)&IF(C10="","",CHAR(10)&"2. "&C10)&IF(C11="","",CHAR(10)&"3. "&C11)&IF(C12="","",CHAR(10)&"4. "&C12)&IF(C13="","",CHAR(10)&"5. "&C13)&IF(C14="","",CHAR(10)&"6. "&C14)&IF(C15="","",CHAR(10)&"7. "&C15)&IF(C16="","",CHAR(10)&"8. "&C16)&IF(C17="","",CHAR(10)&"9. "&C17)&IF(C18="","",CHAR(10)&"10. "&C18)&CHAR(10)&CHAR(10)&"Thank you!") -> Hi there, hope you and the team are well. Before I send the next payment for foundation & footings, please send: 1. Setting-out photo: pegs and strings match the approved plan 2. Trenches with a tape measure showing depth and width 3. Footings poured: photo of every trench 4. Foundation brickwork up to ground level: photo of each side 5. Video walking round the whole foundation 6. Receipts: cement, sand, stone, bricks Thank you!
B23: More ready-made messages
B24: Before work starts: agree the rule | C24: ="Hi "&IF(Project!$B$6="","there",Project!$B$6)&", before we start, here's how I'll handle payments so we're always clear. For each stage I'll send you a short list of photos, a video and receipts. Once I have them, I send the money for the next stage the same day. It's the same for every stage and everyone I work with. Is that OK with you?" -> Hi there, before we start, here's how I'll handle payments so we're always clear. For each stage I'll send you a short list of photos, a video and receipts. Once I have them, I send the money for the next stage the same day. It's the same for every stage and everyone I work with. Is that OK with you?
B25: Proof is late | C25: ="Hi "&IF(Project!$B$6="","there",Project!$B$6)&", just checking in on the photos and video for "&LOWER(C6)&". I'm ready to send the next payment as soon as they come through." -> Hi there, just checking in on the photos and video for foundation & footings. I'm ready to send the next payment as soon as they come through.
B26: Holding a payment politely | C26: ="Hi "&IF(Project!$B$6="","there",Project!$B$6)&", thanks for the update. I'm still missing a few items for "&LOWER(C6)&" (see my list above). I'll release the payment as soon as they're in, so we keep to the agreed system." -> Hi there, thanks for the update. I'm still missing a few items for foundation & footings (see my list above). I'll release the payment as soon as they're in, so we keep to the agreed system.
B27: Price has gone up | C27: ="Hi "&IF(Project!$B$6="","there",Project!$B$6)&", understood. Please send the supplier's quote or receipt showing the new price. Once I see it, I'll update the budget and we can agree the new amount." -> Hi there, understood. Please send the supplier's quote or receipt showing the new price. Once I see it, I'll update the budget and we can agree the new amount.
B28: For family managing the site | C28: ="Hi, thank you so much for keeping an eye on the build, it means a lot. To keep things simple and fair for everyone, I'm using the same system for every stage: photos, a short video and receipts before each payment. Could you help me get these for "&LOWER(C6)&"?" -> Hi, thank you so much for keeping an eye on the build, it means a lot. To keep things simple and fair for everyone, I'm using the same system for every stage: photos, a short video and receipts before each payment. Could you help me get these for foundation & footings?
B29: Payment sent | C29: ="Hi "&IF(Project!$B$6="","there",Project!$B$6)&", I've sent the payment for "&LOWER(C6)&" today. Please confirm when you receive it. Thank you for the good work!" -> Hi there, I've sent the payment for foundation & footings today. Please confirm when you receive it. Thank you for the good work!

Sheet Before You Build
A1: Before you build
A2: Do these checks before you send the first payment. Mark each one Yes when it's done.
B5: Check | C5: Done? | D5: Notes
B6: The stand is legally yours: title deed, or cession / agreement of sale, checked with the Deeds Registry, the council or the developer, in YOUR name | C6: No
B7: You've seen the stand's beacons (in person, by someone you trust, or on a live video call) | C7: No
B8: You know what servicing is done (water, sewer, roads) and what it will cost if it isn't | C8: No
B9: Building plans are approved by the local council before any work starts | C9: No
B10: You've met the builder (in person or on video) and seen at least 2 houses they've built | C10: No
B11: You've spoken to at least one past client of the builder | C11: No
B12: Written agreement signed: what will be built, price per stage, timeline, who buys materials, what happens if work stops | C12: No
B13: Payment schedule agreed: money per stage, and the next stage paid only after proof | C13: No
B14: Proof list sent to the builder before work starts (WhatsApp tab, 'Before work starts') | C14: No
B15: Someone you trust, who isn't the builder, can visit the site now and then | C15: No
B16: Where possible, you pay material suppliers directly and keep their receipts | C16: No
B17: One folder (e.g. Google Drive) for all photos, videos, receipts and agreements | C17: No
B19: Checks done | C19: =COUNTIF(C6:C17,"Yes")&" of 12" -> 0 of 12
B21: Red flags: stop and ask questions if you see these
B22: ⚑ Asks for most of the money up front, before any work
B23: ⚑ Asks you to send money to a different person or account than you agreed
B24: ⚑ Photos are always close-ups, from the same angle, or there's never a video
B25: ⚑ Says 'prices went up' but can't show a supplier quote or receipt
B26: ⚑ Work has stalled, but requests for money keep coming
B27: ⚑ Pressure to pay today: 'the materials will be gone' or 'the price changes tomorrow'
B28: ⚑ Becomes hard to reach right after you send a payment
B29: ⚑ Seller can't show the stand beacons, or rushes you to pay before you've checked ownership
